setup.cfg
setup.py
Endure/__init__.py
Endure/util.py
Endure.egg-info/PKG-INFO
Endure.egg-info/SOURCES.txt
Endure.egg-info/dependency_links.txt
Endure.egg-info/top_level.txt
endure/__init__.py
endure/util.py
endure.egg-info/SOURCES.txt
endure/column/__init__.py
endure/column/options.py
endure/database/__init__.py
endure/query/__init__.py
endure/query/operations.py
endure/table/__init__.py