Metadata-Version: 1.0
Name: endure
Version: 0.3
Summary: A Python database
Home-page: https://gitlab.com/cerebralpower/Endure
Author: Bill Schumacher
Author-email: bill@servernet.co
License: LGPLv3
Keywords: python database db endure
Platform: UNKNOWN
